deepthulac/__init__.py
deepthulac/model_old.py
deepthulac/utils.py
deepthulac/eval/__init__.py
deepthulac/eval/cases.py
deepthulac/eval/old_model.py
deepthulac/eval/test.py
deepthulac/eval/third_party_api.py
deepthulac/legacy/__init__.py
deepthulac/legacy/__main__.py
deepthulac/legacy/base/AlphaBeta.py
deepthulac/legacy/base/Dat.py
deepthulac/legacy/base/Node.py
deepthulac/legacy/base/WordWithTag.py
deepthulac/legacy/base/__init__.py
deepthulac/legacy/base/compatibility.py
deepthulac/legacy/character/CBModel.py
deepthulac/legacy/character/CBNGramFeature.py
deepthulac/legacy/character/CBTaggingDecoder.py
deepthulac/legacy/character/__init__.py
deepthulac/legacy/manage/Filter.py
deepthulac/legacy/manage/Postprocesser.py
deepthulac/legacy/manage/Preprocesser.py
deepthulac/legacy/manage/Punctuation.py
deepthulac/legacy/manage/SoExtention.py
deepthulac/legacy/manage/TimeWord.py
deepthulac/legacy/manage/__init__.py
deepthulac/legacy/manage/verbword.py
deepthulac/seg/__init__.py
deepthulac/seg/cut_sent.py
deepthulac/seg/data_format.py
deepthulac/seg/eval.py
deepthulac/seg/model.py
deepthulac/seg/post_process.py
deepthulac/seg/seg_utils.py
deepthulac/seg/train.py
deepthulac/seg/trie.py
deepthulac-0.1.3.dist-info/LICENSE
deepthulac-0.1.3.dist-info/METADATA
deepthulac-0.1.3.dist-info/WHEEL
deepthulac-0.1.3.dist-info/top_level.txt
deepthulac-0.1.3.dist-info/RECORD
